tabsdata-1.5.0.data/data/bin/apiserver
tabsdata-1.5.0.data/data/bin/bootloader
tabsdata-1.5.0.data/data/bin/supervisor
tabsdata-1.5.0.data/data/bin/tdabout
tabsdata-1.5.0.data/data/bin/tdserver
tabsdata-1.5.0.data/data/bin/transporter
tabsdata-1.5.0.data/purelib/tabsdata/__init__.py
tabsdata-1.5.0.data/purelib/tabsdata/__spec.py
tabsdata-1.5.0.data/purelib/tabsdata/_credentials.py
tabsdata-1.5.0.data/purelib/tabsdata/_decorators.py
tabsdata-1.5.0.data/purelib/tabsdata/_format.py
tabsdata-1.5.0.data/purelib/tabsdata/_globals.py
tabsdata-1.5.0.data/purelib/tabsdata/_secret.py
tabsdata-1.5.0.data/purelib/tabsdata/_tableuri.py
tabsdata-1.5.0.data/purelib/tabsdata/_tabsdatafunction.py
tabsdata-1.5.0.data/purelib/tabsdata/exceptions.py
tabsdata-1.5.0.data/purelib/tabsdata/_cli/__init__.py
tabsdata-1.5.0.data/purelib/tabsdata/_cli/auth_group.py
tabsdata-1.5.0.data/purelib/tabsdata/_cli/cli.py
tabsdata-1.5.0.data/purelib/tabsdata/_cli/cli_utils.py
tabsdata-1.5.0.data/purelib/tabsdata/_cli/collection_group.py
tabsdata-1.5.0.data/purelib/tabsdata/_cli/config_utils.py
tabsdata-1.5.0.data/purelib/tabsdata/_cli/examples_guide.py
tabsdata-1.5.0.data/purelib/tabsdata/_cli/exe_group.py
tabsdata-1.5.0.data/purelib/tabsdata/_cli/fn_group.py
tabsdata-1.5.0.data/purelib/tabsdata/_cli/role_group.py
tabsdata-1.5.0.data/purelib/tabsdata/_cli/table_group.py
tabsdata-1.5.0.data/purelib/tabsdata/_cli/user_group.py
tabsdata-1.5.0.data/purelib/tabsdata/_io/__init__.py
tabsdata-1.5.0.data/purelib/tabsdata/_io/constants.py
tabsdata-1.5.0.data/purelib/tabsdata/_io/plugin.py
tabsdata-1.5.0.data/purelib/tabsdata/_io/connections/__init__.py
tabsdata-1.5.0.data/purelib/tabsdata/_io/connections/connections.py
tabsdata-1.5.0.data/purelib/tabsdata/_io/inputs/__init__.py
tabsdata-1.5.0.data/purelib/tabsdata/_io/inputs/file_inputs.py
tabsdata-1.5.0.data/purelib/tabsdata/_io/inputs/sql_inputs.py
tabsdata-1.5.0.data/purelib/tabsdata/_io/inputs/table_inputs.py
tabsdata-1.5.0.dist-info/licenses/variant/assets/manifest/LICENSE
tabsdata-1.5.0.dist-info/METADATA
tabsdata-1.5.0.dist-info/WHEEL
tabsdata-1.5.0.dist-info/entry_points.txt
tabsdata-1.5.0.dist-info/top_level.txt
tabsdata-1.5.0.dist-info/RECORD
