Metadata-Version: 2.4
Name: tabsdata
Version: 1.5.0
Summary: Tabsdata is a publish-subscribe (pub/sub) server for tables.
Home-page: https://tabsdata.com
Author: Tabs Data Inc.
License: Tabsdata License
Project-URL: Source, https://github.com/tabsdata/tabsdata
Requires-Python: >=3.12
License-File: variant/assets/manifest/LICENSE
Requires-Dist: accessify==0.3.1
Requires-Dist: archspec==0.2.5
Requires-Dist: base32hex==1.0.2
Requires-Dist: click==8.3.0
Requires-Dist: cloudpickle==3.1.1
Requires-Dist: colorama==0.4.6
Requires-Dist: connectorx==0.4.4
Requires-Dist: fastavro==1.12.1
Requires-Dist: fastparquet==2024.11.0
Requires-Dist: filelock==3.20.0
Requires-Dist: humanize==4.14.0
Requires-Dist: hvac==2.3.0
Requires-Dist: ijson==3.4.0
Requires-Dist: importlib_metadata==8.7.0
Requires-Dist: numpy==2.3.4
Requires-Dist: packaging==25.0
Requires-Dist: pandas==2.2.3
Requires-Dist: pillow==12.0.0
Requires-Dist: pip-tools==7.5.1
Requires-Dist: platformdirs==4.5.0
Requires-Dist: polars==1.34.0
Requires-Dist: pycountries==1.2.1
Requires-Dist: PyYAML==6.0.3
Requires-Dist: pyarrow==21.0.0
Requires-Dist: py-cpuinfo==9.0.0
Requires-Dist: pydantic==2.11.10
Requires-Dist: pyiceberg[glue]==0.9.1
Requires-Dist: pywin32==308; platform_system == "Windows"
Requires-Dist: requests==2.32.5
Requires-Dist: rich<14.0.0
Requires-Dist: rich-click==1.9.3
Requires-Dist: ruamel.yaml==0.18.16
Requires-Dist: sqlalchemy==2.0.44
Requires-Dist: starlette==0.49.1
Requires-Dist: typing_extensions==4.15.0
Requires-Dist: tzlocal==5.3.1
Requires-Dist: uuid6==2025.0.1
Requires-Dist: uuid-v7==1.0.0
Requires-Dist: uv==0.9.6
Requires-Dist: tabsdata_bigquery==1.5.0
Requires-Dist: tabsdata_databricks==1.5.0
Requires-Dist: tabsdata_mongodb==1.5.0
Requires-Dist: tabsdata_mssql==1.5.0
Requires-Dist: tabsdata_salesforce==1.5.0
Requires-Dist: tabsdata_snowflake==1.5.0
Provides-Extra: test
Requires-Dist: accessify==0.3.1; extra == "test"
Requires-Dist: archspec==0.2.5; extra == "test"
Requires-Dist: base32hex==1.0.2; extra == "test"
Requires-Dist: click==8.3.0; extra == "test"
Requires-Dist: cloudpickle==3.1.1; extra == "test"
Requires-Dist: colorama==0.4.6; extra == "test"
Requires-Dist: connectorx==0.4.4; extra == "test"
Requires-Dist: fastavro==1.12.1; extra == "test"
Requires-Dist: fastparquet==2024.11.0; extra == "test"
Requires-Dist: filelock==3.20.0; extra == "test"
Requires-Dist: humanize==4.14.0; extra == "test"
Requires-Dist: hvac==2.3.0; extra == "test"
Requires-Dist: ijson==3.4.0; extra == "test"
Requires-Dist: importlib_metadata==8.7.0; extra == "test"
Requires-Dist: numpy==2.3.4; extra == "test"
Requires-Dist: packaging==25.0; extra == "test"
Requires-Dist: pandas==2.2.3; extra == "test"
Requires-Dist: pillow==12.0.0; extra == "test"
Requires-Dist: pip-tools==7.5.1; extra == "test"
Requires-Dist: platformdirs==4.5.0; extra == "test"
Requires-Dist: polars==1.34.0; extra == "test"
Requires-Dist: pycountries==1.2.1; extra == "test"
Requires-Dist: PyYAML==6.0.3; extra == "test"
Requires-Dist: pyarrow==21.0.0; extra == "test"
Requires-Dist: py-cpuinfo==9.0.0; extra == "test"
Requires-Dist: pydantic==2.11.10; extra == "test"
Requires-Dist: pyiceberg[glue]==0.9.1; extra == "test"
Requires-Dist: pywin32==308; platform_system == "Windows" and extra == "test"
Requires-Dist: requests==2.32.5; extra == "test"
Requires-Dist: rich<14.0.0; extra == "test"
Requires-Dist: rich-click==1.9.3; extra == "test"
Requires-Dist: ruamel.yaml==0.18.16; extra == "test"
Requires-Dist: sqlalchemy==2.0.44; extra == "test"
Requires-Dist: starlette==0.49.1; extra == "test"
Requires-Dist: typing_extensions==4.15.0; extra == "test"
Requires-Dist: tzlocal==5.3.1; extra == "test"
Requires-Dist: uuid6==2025.0.1; extra == "test"
Requires-Dist: uuid-v7==1.0.0; extra == "test"
Requires-Dist: uv==0.9.6; extra == "test"
Requires-Dist: tabsdata_bigquery==1.5.0; extra == "test"
Requires-Dist: tabsdata_databricks==1.5.0; extra == "test"
Requires-Dist: tabsdata_mongodb==1.5.0; extra == "test"
Requires-Dist: tabsdata_mssql==1.5.0; extra == "test"
Requires-Dist: tabsdata_salesforce==1.5.0; extra == "test"
Requires-Dist: tabsdata_snowflake==1.5.0; extra == "test"
Requires-Dist: google-cloud-bigquery==3.38.0; extra == "test"
Requires-Dist: databricks-sdk==0.69.0; extra == "test"
Requires-Dist: databricks-sql-connector==4.1.4; extra == "test"
Requires-Dist: pymongo==4.15.3; extra == "test"
Requires-Dist: pyodbc==5.3.0; extra == "test"
Requires-Dist: simple-salesforce==1.12.9; extra == "test"
Requires-Dist: opentelemetry-api==1.38.0; extra == "test"
Requires-Dist: opentelemetry-sdk==1.38.0; extra == "test"
Requires-Dist: snowflake-connector-python==4.0.0; extra == "test"
Requires-Dist: mysql-connector-python==9.5.0; extra == "test"
Requires-Dist: oracledb==3.4.0; extra == "test"
Requires-Dist: psycopg2-binary==2.9.11; extra == "test"
Requires-Dist: ansi2html==1.9.2; extra == "test"
Requires-Dist: azure-storage-blob==12.27.1; extra == "test"
Requires-Dist: black==25.9.0; extra == "test"
Requires-Dist: boto3==1.40.58; extra == "test"
Requires-Dist: build; extra == "test"
Requires-Dist: colorlog==6.10.1; extra == "test"
Requires-Dist: cookiecutter==2.6.0; extra == "test"
Requires-Dist: csvkit==2.1.0; extra == "test"
Requires-Dist: devpi-client==7.2.0; extra == "test"
Requires-Dist: devpi-server==6.17.0; extra == "test"
Requires-Dist: devpi-web==5.0.1; extra == "test"
Requires-Dist: docker==7.1.0; extra == "test"
Requires-Dist: fastapi==0.120.1; extra == "test"
Requires-Dist: flake8==7.3.0; extra == "test"
Requires-Dist: GitPython==3.1.45; extra == "test"
Requires-Dist: gita==0.16.7.3; extra == "test"
Requires-Dist: google-cloud-storage==3.4.1; extra == "test"
Requires-Dist: gTTS; extra == "test"
Requires-Dist: isort==7.0.0; extra == "test"
Requires-Dist: liccheck==0.9.2; extra == "test"
Requires-Dist: licensecheck==2025.1.0; extra == "test"
Requires-Dist: matplotlib==3.10.7; extra == "test"
Requires-Dist: maturin==1.9.6; extra == "test"
Requires-Dist: mimesis==18.0.0; extra == "test"
Requires-Dist: mkdocs==1.6.1; extra == "test"
Requires-Dist: parquet-tools==0.2.16; extra == "test"
Requires-Dist: pdoc==15.0.4; extra == "test"
Requires-Dist: pip-audit==2.9.0; extra == "test"
Requires-Dist: pip-tools==7.5.1; extra == "test"
Requires-Dist: pip-upgrader==1.4.15; extra == "test"
Requires-Dist: pipdeptree==2.29.0; extra == "test"
Requires-Dist: prompt_toolkit==3.0.52; extra == "test"
Requires-Dist: psutil==7.1.1; extra == "test"
Requires-Dist: pydevd; extra == "test"
Requires-Dist: pydevd_pycharm; extra == "test"
Requires-Dist: pygame; extra == "test"
Requires-Dist: pysentry-rs==0.3.12; extra == "test"
Requires-Dist: pytest-check==2.6.0; extra == "test"
Requires-Dist: pytest-cov==7.0.0; extra == "test"
Requires-Dist: pytest-env==1.1.5; extra == "test"
Requires-Dist: pytest-reporter-html1==0.9.5; extra == "test"
Requires-Dist: pytest-timeout==2.4.0; extra == "test"
Requires-Dist: pytest-xdist==3.8.0; extra == "test"
Requires-Dist: pytest==8.4.2; extra == "test"
Requires-Dist: python-dateutil==2.9.0.post0; extra == "test"
Requires-Dist: questionary==2.1.1; extra == "test"
Requires-Dist: setuptools==78.1.1; extra == "test"
Requires-Dist: supervisor==4.2.5; extra == "test"
Requires-Dist: tabulate==0.9.0; extra == "test"
Requires-Dist: tomlkit==0.13.3; extra == "test"
Requires-Dist: tqdm==4.67.1; extra == "test"
Requires-Dist: twine==6.2.0; extra == "test"
Requires-Dist: uvicorn==0.38.0; extra == "test"
Requires-Dist: virtualenv==20.35.3; extra == "test"
Requires-Dist: wheel; extra == "test"
Requires-Dist: wheel-inspect; extra == "test"
Requires-Dist: tabsdata_bigquery[deps]==1.5.0; extra == "test"
Requires-Dist: tabsdata_databricks[deps]==1.5.0; extra == "test"
Requires-Dist: tabsdata_mongodb[deps]==1.5.0; extra == "test"
Requires-Dist: tabsdata_mssql[deps]==1.5.0; extra == "test"
Requires-Dist: tabsdata_salesforce[deps]==1.5.0; extra == "test"
Requires-Dist: tabsdata_snowflake[deps]==1.5.0; extra == "test"
Provides-Extra: snowflake
Requires-Dist: tabsdata_snowflake[deps]==1.5.0; extra == "snowflake"
Provides-Extra: mssql
Requires-Dist: tabsdata_mssql[deps]==1.5.0; extra == "mssql"
Provides-Extra: mongodb
Requires-Dist: tabsdata_mongodb[deps]==1.5.0; extra == "mongodb"
Provides-Extra: salesforce
Requires-Dist: tabsdata_salesforce[deps]==1.5.0; extra == "salesforce"
Provides-Extra: databricks
Requires-Dist: tabsdata_databricks[deps]==1.5.0; extra == "databricks"
Provides-Extra: bigquery
Requires-Dist: tabsdata_bigquery[deps]==1.5.0; extra == "bigquery"
Provides-Extra: all
Requires-Dist: tabsdata_bigquery[deps]==1.5.0; extra == "all"
Requires-Dist: tabsdata_databricks[deps]==1.5.0; extra == "all"
Requires-Dist: tabsdata_mongodb[deps]==1.5.0; extra == "all"
Requires-Dist: tabsdata_mssql[deps]==1.5.0; extra == "all"
Requires-Dist: tabsdata_salesforce[deps]==1.5.0; extra == "all"
Requires-Dist: tabsdata_snowflake[deps]==1.5.0; extra == "all"
Dynamic: author
Dynamic: description
Dynamic: description-content-type
Dynamic: home-page
Dynamic: license
Dynamic: license-file
Dynamic: project-url
Dynamic: provides-extra
Dynamic: requires-dist
Dynamic: requires-python
Dynamic: summary
